{
  "interfaceLanguages": {
    "data": [
      {
        "children": [
          {
            "title": "Media routing",
            "type": "groupMarker"
          }
        ],
        "path": "/documentation/avrouting",
        "title": "AVRouting",
        "type": "module"
      }
    ],
    "occ": [
      {
        "children": [
          {
            "title": "Media routing",
            "type": "groupMarker"
          },
          {
            "children": [
              {
                "title": "Managing authorization",
                "type": "groupMarker"
              },
              {
                "path": "/documentation/avrouting/avcustomroutingcontroller/authorizedroutes",
                "title": "authorizedRoutes",
                "type": "property"
              },
              {
                "path": "/documentation/avrouting/avcustomroutingcontroller/authorizedroutesdidchange",
                "title": "AVCustomRoutingControllerAuthorizedRoutesDidChangeNotification",
                "type": "var"
              },
              {
                "path": "/documentation/avrouting/avcustomroutingcontroller/invalidateauthorization(for:)",
                "title": "- invalidateAuthorizationForRoute:",
                "type": "method"
              },
              {
                "title": "Configuring route addresses",
                "type": "groupMarker"
              },
              {
                "path": "/documentation/avrouting/avcustomroutingcontroller/knownrouteips",
                "title": "knownRouteIPs",
                "type": "property"
              },
              {
                "children": [
                  {
                    "title": "Creating an IP fragment",
                    "type": "groupMarker"
                  },
                  {
                    "path": "/documentation/avrouting/avcustomroutingpartialip/init(address:mask:)",
                    "title": "- initWithAddress:mask:",
                    "type": "method"
                  },
                  {
                    "title": "Inspecting the IP fragment",
                    "type": "groupMarker"
                  },
                  {
                    "path": "/documentation/avrouting/avcustomroutingpartialip/address",
                    "title": "address",
                    "type": "property"
                  },
                  {
                    "path": "/documentation/avrouting/avcustomroutingpartialip/mask",
                    "title": "mask",
                    "type": "property"
                  }
                ],
                "path": "/documentation/avrouting/avcustomroutingpartialip",
                "title": "AVCustomRoutingPartialIP",
                "type": "class"
              },
              {
                "title": "Activating a route",
                "type": "groupMarker"
              },
              {
                "path": "/documentation/avrouting/avcustomroutingcontroller/isrouteactive(_:)",
                "title": "- isRouteActive:",
                "type": "method"
              },
              {
                "path": "/documentation/avrouting/avcustomroutingcontroller/setactive(_:for:)",
                "title": "- setActive:forRoute:",
                "type": "method"
              },
              {
                "title": "Accessing the delegate",
                "type": "groupMarker"
              },
              {
                "path": "/documentation/avrouting/avcustomroutingcontroller/delegate",
                "title": "delegate",
                "type": "property"
              },
              {
                "title": "Customizing the user interface",
                "type": "groupMarker"
              },
              {
                "path": "/documentation/avrouting/avcustomroutingcontroller/customactionitems",
                "title": "customActionItems",
                "type": "property"
              }
            ],
            "path": "/documentation/avrouting/avcustomroutingcontroller",
            "title": "AVCustomRoutingController",
            "type": "class"
          },
          {
            "children": [
              {
                "title": "Handling controller events",
                "type": "groupMarker"
              },
              {
                "path": "/documentation/avrouting/avcustomroutingcontrollerdelegate/customroutingcontroller(_:handle:completionhandler:)",
                "title": "- customRoutingController:handleEvent:completionHandler:",
                "type": "method"
              },
              {
                "path": "/documentation/avrouting/avcustomroutingcontrollerdelegate/customroutingcontroller(_:eventdidtimeout:)",
                "title": "- customRoutingController:eventDidTimeOut:",
                "type": "method"
              },
              {
                "path": "/documentation/avrouting/avcustomroutingcontrollerdelegate/customroutingcontroller(_:didselect:)",
                "title": "- customRoutingController:didSelectItem:",
                "type": "method"
              }
            ],
            "path": "/documentation/avrouting/avcustomroutingcontrollerdelegate",
            "title": "AVCustomRoutingControllerDelegate",
            "type": "protocol"
          },
          {
            "children": [
              {
                "title": "Inspecting an event",
                "type": "groupMarker"
              },
              {
                "path": "/documentation/avrouting/avcustomroutingevent/route",
                "title": "route",
                "type": "property"
              },
              {
                "children": [
                  {
                    "title": "Identifying routes",
                    "type": "groupMarker"
                  },
                  {
                    "path": "/documentation/avrouting/avcustomdeviceroute/bluetoothidentifier",
                    "title": "bluetoothIdentifier",
                    "type": "property"
                  },
                  {
                    "path": "/documentation/avrouting/avcustomdeviceroute/networkendpoint",
                    "title": "networkEndpoint",
                    "type": "property"
                  }
                ],
                "path": "/documentation/avrouting/avcustomdeviceroute",
                "title": "AVCustomDeviceRoute",
                "type": "class"
              },
              {
                "path": "/documentation/avrouting/avcustomroutingevent/reason",
                "title": "reason",
                "type": "property"
              },
              {
                "children": [
                  {
                    "title": "Reasons",
                    "type": "groupMarker"
                  },
                  {
                    "path": "/documentation/avrouting/avcustomroutingeventreason/activate",
                    "title": "AVCustomRoutingEventReasonActivate",
                    "type": "case"
                  },
                  {
                    "path": "/documentation/avrouting/avcustomroutingeventreason/deactivate",
                    "title": "AVCustomRoutingEventReasonDeactivate",
                    "type": "case"
                  },
                  {
                    "path": "/documentation/avrouting/avcustomroutingeventreason/reactivate",
                    "title": "AVCustomRoutingEventReasonReactivate",
                    "type": "case"
                  }
                ],
                "path": "/documentation/avrouting/avcustomroutingeventreason",
                "title": "AVCustomRoutingEventReason",
                "type": "enum"
              }
            ],
            "path": "/documentation/avrouting/avcustomroutingevent",
            "title": "AVCustomRoutingEvent",
            "type": "class"
          },
          {
            "children": [
              {
                "title": "Configuring an item",
                "type": "groupMarker"
              },
              {
                "path": "/documentation/avrouting/avcustomroutingactionitem/type",
                "title": "type",
                "type": "property"
              },
              {
                "path": "/documentation/avrouting/avcustomroutingactionitem/overridetitle",
                "title": "overrideTitle",
                "type": "property"
              }
            ],
            "path": "/documentation/avrouting/avcustomroutingactionitem",
            "title": "AVCustomRoutingActionItem",
            "type": "class"
          }
        ],
        "path": "/documentation/avrouting",
        "title": "AVRouting",
        "type": "module"
      }
    ],
    "swift": [
      {
        "children": [
          {
            "title": "Media routing",
            "type": "groupMarker"
          },
          {
            "children": [
              {
                "title": "Managing authorization",
                "type": "groupMarker"
              },
              {
                "path": "/documentation/avrouting/avcustomroutingcontroller/authorizedroutes",
                "title": "var authorizedRoutes: [AVCustomDeviceRoute]",
                "type": "property"
              },
              {
                "path": "/documentation/avrouting/avcustomroutingcontroller/authorizedroutesdidchange",
                "title": "class let authorizedRoutesDidChange: NSNotification.Name",
                "type": "property"
              },
              {
                "path": "/documentation/avrouting/avcustomroutingcontroller/invalidateauthorization(for:)",
                "title": "func invalidateAuthorization(for: AVCustomDeviceRoute)",
                "type": "method"
              },
              {
                "title": "Configuring route addresses",
                "type": "groupMarker"
              },
              {
                "path": "/documentation/avrouting/avcustomroutingcontroller/knownrouteips",
                "title": "var knownRouteIPs: [AVCustomRoutingPartialIP]",
                "type": "property"
              },
              {
                "children": [
                  {
                    "title": "Creating an IP fragment",
                    "type": "groupMarker"
                  },
                  {
                    "path": "/documentation/avrouting/avcustomroutingpartialip/init(address:mask:)",
                    "title": "init(address: Data, mask: Data)",
                    "type": "init"
                  },
                  {
                    "title": "Inspecting the IP fragment",
                    "type": "groupMarker"
                  },
                  {
                    "path": "/documentation/avrouting/avcustomroutingpartialip/address",
                    "title": "var address: Data",
                    "type": "property"
                  },
                  {
                    "path": "/documentation/avrouting/avcustomroutingpartialip/mask",
                    "title": "var mask: Data",
                    "type": "property"
                  }
                ],
                "path": "/documentation/avrouting/avcustomroutingpartialip",
                "title": "AVCustomRoutingPartialIP",
                "type": "class"
              },
              {
                "title": "Activating a route",
                "type": "groupMarker"
              },
              {
                "path": "/documentation/avrouting/avcustomroutingcontroller/isrouteactive(_:)",
                "title": "func isRouteActive(AVCustomDeviceRoute) -> Bool",
                "type": "method"
              },
              {
                "path": "/documentation/avrouting/avcustomroutingcontroller/setactive(_:for:)",
                "title": "func setActive(Bool, for: AVCustomDeviceRoute)",
                "type": "method"
              },
              {
                "title": "Accessing the delegate",
                "type": "groupMarker"
              },
              {
                "path": "/documentation/avrouting/avcustomroutingcontroller/delegate",
                "title": "var delegate: (any AVCustomRoutingControllerDelegate)?",
                "type": "property"
              },
              {
                "title": "Customizing the user interface",
                "type": "groupMarker"
              },
              {
                "path": "/documentation/avrouting/avcustomroutingcontroller/customactionitems",
                "title": "var customActionItems: [AVCustomRoutingActionItem]",
                "type": "property"
              }
            ],
            "path": "/documentation/avrouting/avcustomroutingcontroller",
            "title": "AVCustomRoutingController",
            "type": "class"
          },
          {
            "children": [
              {
                "title": "Handling controller events",
                "type": "groupMarker"
              },
              {
                "path": "/documentation/avrouting/avcustomroutingcontrollerdelegate/customroutingcontroller(_:handle:completionhandler:)",
                "title": "func customRoutingController(AVCustomRoutingController, handle: AVCustomRoutingEvent, completionHandler: (Bool) -> Void)",
                "type": "method"
              },
              {
                "path": "/documentation/avrouting/avcustomroutingcontrollerdelegate/customroutingcontroller(_:eventdidtimeout:)",
                "title": "func customRoutingController(AVCustomRoutingController, eventDidTimeOut: AVCustomRoutingEvent)",
                "type": "method"
              },
              {
                "path": "/documentation/avrouting/avcustomroutingcontrollerdelegate/customroutingcontroller(_:didselect:)",
                "title": "func customRoutingController(AVCustomRoutingController, didSelect: AVCustomRoutingActionItem)",
                "type": "method"
              }
            ],
            "path": "/documentation/avrouting/avcustomroutingcontrollerdelegate",
            "title": "AVCustomRoutingControllerDelegate",
            "type": "protocol"
          },
          {
            "children": [
              {
                "title": "Inspecting an event",
                "type": "groupMarker"
              },
              {
                "path": "/documentation/avrouting/avcustomroutingevent/route",
                "title": "var route: AVCustomDeviceRoute",
                "type": "property"
              },
              {
                "children": [
                  {
                    "title": "Identifying routes",
                    "type": "groupMarker"
                  },
                  {
                    "path": "/documentation/avrouting/avcustomdeviceroute/bluetoothidentifier",
                    "title": "var bluetoothIdentifier: UUID?",
                    "type": "property"
                  },
                  {
                    "path": "/documentation/avrouting/avcustomdeviceroute/networkendpoint",
                    "title": "var networkEndpoint: nw_endpoint_t?",
                    "type": "property"
                  }
                ],
                "path": "/documentation/avrouting/avcustomdeviceroute",
                "title": "AVCustomDeviceRoute",
                "type": "class"
              },
              {
                "path": "/documentation/avrouting/avcustomroutingevent/reason",
                "title": "var reason: AVCustomRoutingEventReason",
                "type": "property"
              },
              {
                "children": [
                  {
                    "title": "Reasons",
                    "type": "groupMarker"
                  },
                  {
                    "path": "/documentation/avrouting/avcustomroutingeventreason/activate",
                    "title": "case activate",
                    "type": "case"
                  },
                  {
                    "path": "/documentation/avrouting/avcustomroutingeventreason/deactivate",
                    "title": "case deactivate",
                    "type": "case"
                  },
                  {
                    "path": "/documentation/avrouting/avcustomroutingeventreason/reactivate",
                    "title": "case reactivate",
                    "type": "case"
                  },
                  {
                    "title": "Initializers",
                    "type": "groupMarker"
                  },
                  {
                    "path": "/documentation/avrouting/avcustomroutingeventreason/init(rawvalue:)",
                    "title": "init?(rawValue: Int)",
                    "type": "init"
                  }
                ],
                "path": "/documentation/avrouting/avcustomroutingeventreason",
                "title": "AVCustomRoutingEventReason",
                "type": "enum"
              }
            ],
            "path": "/documentation/avrouting/avcustomroutingevent",
            "title": "AVCustomRoutingEvent",
            "type": "class"
          },
          {
            "children": [
              {
                "title": "Configuring an item",
                "type": "groupMarker"
              },
              {
                "path": "/documentation/avrouting/avcustomroutingactionitem/type",
                "title": "var type: UTType",
                "type": "property"
              },
              {
                "path": "/documentation/avrouting/avcustomroutingactionitem/overridetitle",
                "title": "var overrideTitle: String?",
                "type": "property"
              }
            ],
            "path": "/documentation/avrouting/avcustomroutingactionitem",
            "title": "AVCustomRoutingActionItem",
            "type": "class"
          }
        ],
        "path": "/documentation/avrouting",
        "title": "AVRouting",
        "type": "module"
      }
    ]
  },
  "schemaVersion": {
    "major": 0,
    "minor": 1,
    "patch": 0
  }
}
